hpcom/__init__.py
hpcom/_sklearn_functions.py
hpcom/channel.py
hpcom/decorators.py
hpcom/hpcom_old.py
hpcom/metrics.py
hpcom/modulation.py
hpcom/plot.py
hpcom/signal.py
hpcom-0.1.13.dist-info/LICENSE
hpcom-0.1.13.dist-info/METADATA
hpcom-0.1.13.dist-info/WHEEL
hpcom-0.1.13.dist-info/top_level.txt
hpcom-0.1.13.dist-info/RECORD
