Metadata-Version: 2.1
Name: hpcom
Version: 0.1.13
Summary: High performance optical communication library
Author-email: Egor Sedov <e.sedov@g.nsu.ru>
License: GNU GENERAL PUBLIC LICENSE
Project-URL: Homepage, https://github.com/esf0/hpcom
Project-URL: Bug Tracker, https://github.com/esf0/hpcom/issues
Classifier: Programming Language :: Python :: 3
Classifier: License :: OSI Approved :: GNU General Public License v3 (GPLv3)
Classifier: Operating System :: OS Independent
Classifier: Development Status :: 2 - Pre-Alpha
Classifier: Topic :: Scientific/Engineering
Requires-Python: >=3.7
License-File: LICENSE
